webcam_mcp/__init__.py
webcam_mcp/camera.py
webcam_mcp/cli.py
webcam_mcp/config.py
webcam_mcp/server.py
webcam_mcp-0.1.2.dist-info/METADATA
webcam_mcp-0.1.2.dist-info/WHEEL
webcam_mcp-0.1.2.dist-info/entry_points.txt
webcam_mcp-0.1.2.dist-info/licenses/LICENSE
webcam_mcp-0.1.2.dist-info/RECORD
