Metadata-Version: 2.4
Name: webcam-mcp
Version: 0.1.2
Summary: MCP server for webcam access - capture photos and video for LLM agents
Project-URL: Homepage, https://github.com/modelcontextprotocol/servers
Project-URL: Repository, https://github.com/modelcontextprotocol/servers
Project-URL: Issues, https://github.com/modelcontextprotocol/servers/issues
Author: Pavel Kirienko <pavel.kirienko@zubax.com>
License: MIT
License-File: LICENSE
Keywords: agent,camera,llm,mcp,model-context-protocol,webcam
Classifier: Intended Audience :: Developers
Classifier: License :: OSI Approved :: MIT License
Classifier: Programming Language :: Python :: 3
Classifier: Topic :: Multimedia :: Video :: Capture
Classifier: Topic :: Software Development :: Libraries :: Python Modules
Requires-Python: >=3.10
Requires-Dist: mcp<2.0.0,>=1.6.0
Requires-Dist: opencv-python-headless<5.0.0,>=4.8.0
Provides-Extra: dev
Requires-Dist: pytest; extra == 'dev'
Requires-Dist: pytest-asyncio; extra == 'dev'
Requires-Dist: pytest-mock; extra == 'dev'
Requires-Dist: ruff; extra == 'dev'
